Topsis_101903239_Pushpak/__init__.py
Topsis_Pushpak/__init__.py
Topsis_Pushpak_101903239/__init__.py
Topsis_101903239_Pushpak-1.0.dist-info/LICENSE.txt
Topsis_101903239_Pushpak-1.0.dist-info/METADATA
Topsis_101903239_Pushpak-1.0.dist-info/WHEEL
Topsis_101903239_Pushpak-1.0.dist-info/top_level.txt
Topsis_101903239_Pushpak-1.0.dist-info/RECORD
